ecutils/__init__.py
ecutils/algorithms.py
ecutils/core.py
ecutils/curves.py
ecutils/protocols.py
ecutils/settings.py
ecutils/utils.py
ecutils-1.1.5.dist-info/METADATA
ecutils-1.1.5.dist-info/WHEEL
ecutils-1.1.5.dist-info/licenses/LICENSE.md
ecutils-1.1.5.dist-info/RECORD
