Metadata-Version: 2.4
Name: ecutils
Version: 1.1.5
Summary: Python Library for Elliptic Curve Cryptography: key exchanges (Diffie-Hellman, Massey-Omura), ECDSA signatures, and Koblitz encoding. Suitable for crypto education and secure systems.
Project-URL: Homepage, https://ecutils.readthedocs.io/en/stable/
Project-URL: Documentation, https://ecutils.readthedocs.io/en/stable/
Project-URL: Repository, https://github.com/isakruas/ecutils.git
Project-URL: Bug Tracker, https://github.com/isakruas/ecutils/issues
Project-URL: Changelog, https://github.com/isakruas/ecutils/blob/master/CHANGELOG.md
Author-email: Isak Paulo de Andrade Ruas <isakruas@gmail.com>, Celimar Reijane Alves Damasceno Paiva <celimar.damasceno@ifnmg.edu.br>, Fernando Marcos Souza Silva <fernando.silva@ifnmg.edu.br>
Maintainer-email: Isak Paulo de Andrade Ruas <isakruas@gmail.com>
License: MIT
License-File: LICENSE.md
Keywords: cryptographic-algorithms,diffie-hellman-key-exchange,digital-signatures,ec,ecc-based-protocols,ecdh,ecdsa,eck,ecmo,ecutils,elliptic-curve-cryptography,elliptic-curve-operation,koblitz-encoding,massey-omura-protocol,message-encoding-and-decoding,public-key-cryptography,python-cryptography,secure-communication
Classifier: Development Status :: 5 - Production/Stable
Classifier: Development Status :: 6 - Mature
Classifier: Environment :: Console
Classifier: Intended Audience :: Developers
Classifier: Intended Audience :: Education
Classifier: Intended Audience :: Science/Research
Classifier: License :: OSI Approved :: MIT License
Classifier: Natural Language :: English
Classifier: Operating System :: OS Independent
Classifier: Programming Language :: Python :: 3.9
Classifier: Programming Language :: Python :: 3.10
Classifier: Programming Language :: Python :: 3.11
Classifier: Topic :: Software Development :: Build Tools
Classifier: Topic :: Software Development :: Libraries
Requires-Python: >=3.9
